taxjar/__init__.py
taxjar/client.py
taxjar/exceptions.py
taxjar/factory.py
taxjar/response.py
taxjar/data/__init__.py
taxjar/data/address.py
taxjar/data/breakdown.py
taxjar/data/breakdown_line_item.py
taxjar/data/category.py
taxjar/data/customer.py
taxjar/data/exempt_region.py
taxjar/data/float_property.py
taxjar/data/iterable.py
taxjar/data/jurisdictions.py
taxjar/data/line_item.py
taxjar/data/order.py
taxjar/data/rate.py
taxjar/data/region.py
taxjar/data/shipping.py
taxjar/data/summary_rate.py
taxjar/data/tax.py
taxjar/data/validation.py
taxjar-2.0.1.dist-info/licenses/LICENSE.txt
taxjar-2.0.1.dist-info/METADATA
taxjar-2.0.1.dist-info/WHEEL
taxjar-2.0.1.dist-info/top_level.txt
taxjar-2.0.1.dist-info/RECORD
